{
  "type": "node",
  "name": "Service Provider Categories",
  "value": 0,
  "children": [
    {
      "type": "node",
      "name": "Digital Asset Custody",
      "value": 0,
      "children": [
        {
          "type": "leaf",
          "id": "sp_fireblocks",
          "name": "Fireblocks",
          "value": 50,
          "icon": "/icons/Service Providers/digital-asset-category/fireblock.jpeg",
          "details": "A platform providing secure digital asset custody and transfer solutions.",
          "link": "https://www.fireblocks.com/"
        },
        {
          "type": "leaf",
          "id": "sp_komainu",
          "name": "Komainu",
          "value": 50,
          "icon": "/icons/Service Providers/digital-asset-category/komainu.webp",
          "details": "Komainu offers secure digital asset custody services, providing institutional-grade security for crypto assets.",
          "link": "https://komainu.com/"
        },
        {
          "type": "leaf",
          "id": "sp_anchorage",
          "name": "Anchorage Digital",
          "value": 50,
          "icon": "/icons/Service Providers/digital-asset-category/anchorage.png",
          "details": "Anchorage provides secure custody solutions for digital assets with a focus on institutional clients and regulatory compliance.",
          "link": "https://www.anchorage.com/"
        },
        {
          "type": "leaf",
          "id": "sp_bit_go",
          "name": "BitGo",
          "value": 50,
          "icon": "/icons/Service Providers/digital-asset-category/bitgo.png",
          "details": "BitGo provides secure custody solutions for digital assets, offering multi-signature wallets and institutional-grade security.",
          "link": "https://www.bitgo.com/"
        },
        {
          "type": "leaf",
          "id": "sp_copper",
          "name": "Copper",
          "value": 50,
          "icon": "/icons/Service Providers/digital-asset-category/copper.webp",
          "details": "Copper offers institutional-grade custody solutions for digital assets, providing both security and operational services.",
          "link": "https://copper.co/"
        }
      ]
    },
    {
      "type": "node",
      "name": "Smart Contract Audit",
      "value": 0,
      "children": [
        {
          "type": "leaf",
          "id": "sp_open_zeppelin",
          "name": "OpenZeppelin",
          "value": 50,
          "icon": "/icons/Service Providers/smart-contract-audit/openzeppelin.png",
          "details": "A company specializing in smart contract security audits and blockchain development frameworks.",
          "link": "https://www.openzeppelin.com/"
        },
        {
          "type": "leaf",
          "id": "sp_immunefi",
          "name": "Immunefi",
          "value": 50,
          "icon": "/icons/Service Providers/smart-contract-audit/immunefi.png",
          "details": "Offers bug bounty programs and security audits for decentralized applications.",
          "link": "https://immunefi.com/"
        },
        {
          "type": "leaf",
          "id": "sp_quantstamp",
          "name": "Quantstamp",
          "value": 50,
          "icon": "/icons/Service Providers/smart-contract-audit/quantstamp.png",
          "details": "Provides security audits for smart contracts and blockchain projects.",
          "link": "https://quantstamp.com/"
        },
        {
          "type": "leaf",
          "id": "sp_trail_of_bits",
          "name": "Trail of Bits",
          "value": 50,
          "icon": "/icons/Service Providers/smart-contract-audit/trail-of-bits.svg",
          "details": "Provides security audits and assessments for smart contracts and blockchain applications.",
          "link": "https://www.trailofbits.com/"
        }
      ]
    },
    {
      "type": "node",
      "name": "Asset/Fund Management",
      "value": 0,
      "children": [
        {
          "type": "leaf",
          "id": "sp_eq_capital",
          "name": "EQ Capital",
          "value": 50,
          "icon": "/icons/Service Providers/asset-fund/eqcapital.png",
          "details": "Investment management firm specializing in portfolio optimization and wealth management.",
          "link": "https://equilibriacapital.com/"
        },
        {
          "type": "leaf",
          "id": "sp_lymon",
          "name": "Lymon",
          "value": 50,
          "icon": "/icons/Service Providers/asset-fund/lymon.png",
          "details": "Consultancy firm providing financial and legal advisory services.",
          "link": "https://www.lymon.com.sg/"
        },
        {
          "type": "leaf",
          "id": "sp_protege_fund_services",
          "name": "Protege Fund Services",
          "value": 50,
          "icon": "/icons/Service Providers/asset-fund/protege.jpg",
          "details": "Fund administration services, including financial reporting and valuation.",
          "link": "https://www.protegefs.com/"
        },
        {
          "type": "leaf",
          "id": "sp_state_street",
          "name": "State Street",
          "value": 50,
          "icon": "/icons/Service Providers/asset-fund/state-street.png",
          "details": "A leading provider of financial services to institutional investors, including investment servicing and management.",
          "link": "https://www.statestreet.com/"
        },
        {
          "type": "leaf",
          "id": "sp_stonex",
          "name": "StoneX",
          "value": 50,
          "icon": "/icons/Service Providers/asset-fund/stonex.png",
          "details": "A global financial services network providing execution, clearing, and advisory services.",
          "link": "https://www.stonex.com/"
        },
        {
          "type": "leaf",
          "id": "sp_black_rock",
          "name": "BlackRock",
          "value": 50,
          "icon": "/icons/Service Providers/asset-fund/blackrock.png",
          "details": "A global investment management corporation that manages assets and provides investment services.",
          "link": "https://www.blackrock.com/"
        },
        {
          "type": "leaf",
          "id": "sp_kinza_finance",
          "name": "Kinza Finance",
          "value": 50,
          "icon": "/icons/Service Providers/asset-fund/kinza.webp",
          "details": "A decentralized lending platform that allows users to stake real-world asset tokens for over-collateralized lending.",
          "link": "https://kinza.finance/"
        },
        {
          "type": "leaf",
          "id": "sp_room40",
          "name": "Room40",
          "value": 50,
          "icon": "/icons/Service Providers/asset-fund/room40.jpg",
          "details": "Room40 is an institutional investment firm that manages a portfolio of U.S. Treasury bills and reverse repurchase agreements for the Cash Management Pool.",
          "link": "https://www.room40.capital/"
        },
        {
          "type": "leaf",
          "id": "sp_lukka",
          "name": "Lukka",
          "value": 50,
          "icon": "/icons/Service Providers/asset-fund/lukka.webp",
          "details": "Provides cryptocurrency data services for tax, accounting, and compliance.",
          "link": "https://www.lukka.tech/"
        },
        {
          "type": "leaf",
          "id": "sp_federated_hermes",
          "name": "Federated Hermes, Inc.",
          "value": 50,
          "icon": "/icons/Service Providers/asset-fund/federated.jpg",
          "details": "Acts as a sub-advisor providing specialized investment insights and strategies.",
          "link": "https://www.federatedhermes.com/"
        },
        {
          "type": "leaf",
          "id": "sp_nav_consulting",
          "name": "NAV Consulting",
          "value": 50,
          "icon": "/icons/Service Providers/asset-fund/nav.webp",
          "details": "NAV calculation services for accurately determining asset values.",
          "link": "https://www.navfundservices.com/"
        },
        {
          "type": "leaf",
          "id": "sp_marex",
          "name": "Marex",
          "value": 50,
          "icon": "/icons/Service Providers/asset-fund/marex.jpg",
          "details": "Marex provides asset management services, including fund management and trading solutions for institutional clients.",
          "link": "https://www.marex.com/"
        },
        {
          "type": "leaf",
          "id": "sp_ultimus",
          "name": "Ultimus",
          "value": 50,
          "icon": "/icons/Service Providers/asset-fund/ultimus.jpg",
          "details": "Ultimus provides fund administration and management services, including reporting and compliance solutions for asset managers.",
          "link": "https://www.ultimusfundsolutions.com/"
        },
        {
          "type": "leaf",
          "id": "sp_arca",
          "name": "Arca",
          "value": 50,
          "icon": "/icons/Service Providers/asset-fund/arca.webp",
          "details": "Arca is a leading digital asset investment firm, providing digital asset management and blockchain-based financial services.",
          "link": "https://www.ar.ca/"
        },
        {
          "type": "leaf",
          "id": "sp_truefi",
          "name": "TrueFi",
          "value": 50,
          "icon": "/icons/Service Providers/asset-fund/truefi.png",
          "details": "TrueFi is a decentralized finance (DeFi) lending protocol offering uncollateralized loans to institutional borrowers, enabling them to access liquidity in a trustless, transparent manner.",
          "link": "https://www.truefi.io/"
        },
        {
          "type": "leaf",
          "id": "sp_archblock",
          "name": "Archblock",
          "value": 50,
          "icon": "/icons/Service Providers/asset-fund/archblock.png",
          "details": "Archblock is a blockchain technology company providing secure tokenization and asset-backed solutions, enabling businesses to create and manage tokenized real-world assets.",
          "link": "https://www.archblock.com/"
        }
      ]
    },
    {
      "type": "node",
      "name": "Auditor",
      "value": 0,
      "children": [
        {
          "type": "leaf",
          "id": "sp_network_firm",
          "name": "The Network Firm",
          "value": 50,
          "icon": "/icons/Service Providers/auditor/network-firm.png",
          "details": "An auditing firm providing comprehensive financial audit and assurance services.",
          "link": "https://www.thenetworkfirm.com/"
        },
        {
          "type": "leaf",
          "id": "sp_ernst_young_llp",
          "name": "Ernst & Young LLP",
          "value": 50,
          "icon": "/icons/Service Providers/auditor/ernst-young-llp.png",
          "details": "A multinational professional services firm providing auditing, tax, and advisory services.",
          "link": "https://www.ey.com/"
        },
        {
          "type": "leaf",
          "id": "sp_kpmg",
          "name": "KPMG",
          "value": 50,
          "icon": "/icons/Service Providers/auditor/kpmg.png",
          "details": "A global network of professional services firms providing audit, tax, and advisory services.",
          "link": "https://home.kpmg/"
        },
        {
          "type": "leaf",
          "id": "sp_steakhouse_financial",
          "name": "Steakhouse Financial",
          "value": 50,
          "icon": "/icons/Service Providers/auditor/steakhouse.svg",
          "details": "Provides third-party financial signing services for secure transactions.",
          "link": "https://www.steakhouse.financial/"
        },
        {
          "type": "leaf",
          "id": "sp_nav_consulting",
          "name": "NAV Consulting",
          "value": 50,
          "icon": "/icons/Service Providers/auditor/nav.webp",
          "details": "NAV calculation services for accurately determining asset values.",
          "link": "https://www.navfundservices.com/"
        },
        {
          "type": "leaf",
          "id": "sp_nephos",
          "name": "Nephos (Attestation)",
          "value": 50,
          "icon": "/icons/Service Providers/auditor/nephos.png",
          "details": "Offers verification and attestation services for financial statements and compliance.",
          "link": "https://nephosgroup.co/"
        },
        {
          "type": "leaf",
          "id": "sp_cohen_company",
          "name": "Cohen and Company",
          "value": 50,
          "icon": "/icons/Service Providers/auditor/cohenco.jpg",
          "details": "Cohen and Company offers audit, tax, and advisory services to a broad range of clients, including businesses in the financial and crypto sectors.",
          "link": "https://www.cohencpa.com/"
        },
        {
          "type": "leaf",
          "id": "sp_rsm",
          "name": "RSM",
          "value": 50,
          "icon": "/icons/Service Providers/auditor/rsm.png",
          "details": "RSM is a global audit and advisory firm, offering professional services to clients in the crypto, financial, and tech sectors.",
          "link": "https://rsmus.com/"
        },
        {
          "type": "leaf",
          "id": "sp_sigma_prime",
          "name": "Sigma Prime",
          "value": 50,
          "icon": "/icons/Service Providers/auditor/sigmaprime.png",
          "details": "Sigma Prime is a blockchain security firm offering smart contract audits, code reviews, and consulting services to improve the security and functionality of decentralized systems.",
          "link": "https://sigmaprime.io/"
        },
        {
          "type": "leaf",
          "id": "sp_runtime_verification",
          "name": "Runtime Verification",
          "value": 50,
          "icon": "/icons/Service Providers/auditor/runtime_verification.png",
          "details": "Runtime Verification provides formal verification services for smart contracts, ensuring that smart contracts behave as intended and adhere to desired properties.",
          "link": "https://runtimeverification.com/"
        },
        {
          "type": "leaf",
          "id": "sp_dedaub",
          "name": "Dedaub",
          "value": 50,
          "icon": "/icons/Service Providers/auditor/dedaub.jpeg",
          "details": "Dedaub is a leading provider of smart contract auditing and security services, specializing in formal verification and security assessments for decentralized applications.",
          "link": "https://dedaub.com/"
        },
        {
          "type": "leaf",
          "id": "sp_certora",
          "name": "Certora",
          "value": 50,
          "icon": "/icons/Service Providers/auditor/certora.jpeg",
          "details": "Certora offers formal verification solutions for smart contracts to ensure that decentralized systems are secure, bug-free, and function as expected under all conditions.",
          "link": "https://www.certora.com/"
        },
        {
          "type": "leaf",
          "id": "sp_ottersec",
          "name": "OtterSec",
          "value": 50,
          "icon": "/icons/Service Providers/auditor/ottersec.jpeg",
          "details": "OtterSec is a blockchain security firm that offers smart contract auditing and vulnerability assessments for decentralized finance (DeFi) projects. Their services help identify and mitigate risks, ensuring the integrity and security of blockchain applications. ",
          "link": "https://osec.io/"
        }
      ]
    },
    {
      "type": "node",
      "name": "Onramp",
      "value": 0,
      "children": [
        {
          "type": "leaf",
          "id": "sp_coinbase",
          "name": "Coinbase",
          "value": 50,
          "icon": "/icons/Service Providers/onramp/coinbase.webp",
          "details": "A prime brokerage service by Coinbase for secure fiat-to-crypto onramping.",
          "link": "https://www.coinbase.com"
        },
        {
          "type": "leaf",
          "id": "sp_circle",
          "name": "Circle",
          "value": 50,
          "icon": "/icons/Service Providers/onramp/circle.png",
          "details": "A global financial technology firm that provides internet-based payment and treasury infrastructure.",
          "link": "https://www.circle.com/"
        },
        {
          "type": "leaf",
          "id": "sp_monerium",
          "name": "Monerium",
          "value": 50,
          "icon": "/icons/Service Providers/onramp/monerium.png",
          "details": "Monerium issues EURe, the first fully authorized and regulated euro stablecoin.",
          "link": "https://monerium.com/"
        },
        {
          "type": "leaf",
          "id": "sp_theter",
          "name": "Tether",
          "value": 50,
          "icon": "",
          "details": "Tether tokens are the most widely adopted stablecoins, having pioneered the concept in the digital token space.",
          "link": "https://tether.tkyc_aml_complianceo/"
        },
        {
          "type": "leaf",
          "id": "sp_zero_hash",
          "name": "Zero Hash",
          "value": 50,
          "icon": "/icons/Service Providers/onramp/zero-hash.webp",
          "details": "Zero Hash provides infrastructure for onramping digital assets, enabling secure fiat-to-crypto transactions for institutions.",
          "link": "https://www.zerohash.com/"
        },
        {
          "type": "leaf",
          "id": "sp_moonpay",
          "name": "MoonPay",
          "value": 50,
          "icon": "/icons/Service Providers/onramp/moonpay.png",
          "details": "MoonPay is a global payment gateway that allows users to purchase cryptocurrencies using traditional payment methods like credit cards, debit cards, bank transfers, and other payment methods. It serves as an on-ramp for users to convert fiat currencies into cryptocurrencies like Bitcoin, Ethereum, and others.",
          "link": "https://www.moonpay.com/"
        }
      ]
    },
    {
      "type": "node",
      "name": "Custodian",
      "value": 0,
      "children": [
        {
          "type": "leaf",
          "id": "sp_umb",
          "name": "UMB Bank, N.A.",
          "value": 50,
          "icon": "/icons/Service Providers/custodian/umb.jpg",
          "details": "Provides custodial services for safeguarding financial assets.",
          "link": "https://www.umb.com/"
        },
        {
          "type": "leaf",
          "id": "sp_ankura",
          "name": "Ankura Trust Company",
          "value": 50,
          "icon": "/icons/Service Providers/custodian/ankura.png",
          "details": "A leading provider of custodial services for managing assets.",
          "link": "https://www.ankuratrust.com/"
        },
        {
          "type": "leaf",
          "id": "sp_bnp_paribas",
          "name": "BNP Paribas",
          "value": 50,
          "icon": "/icons/Service Providers/custodian/bnp.png",
          "details": "A leading global bank providing financial services and investment solutions.",
          "link": "https://group.bnpparibas/"
        }
      ]
    },
    {
      "type": "node",
      "name": "Regulator",
      "value": 0,
      "children": [
        {
          "type": "leaf",
          "id": "sp_financial_services_commision",
          "name": "FSC",
          "value": 50,
          "icon": "/icons/Service Providers/regulator/fsc.png",
          "details": "Regulatory authority overseeing financial services.",
          "link": "https://www.bvifsc.vg/"
        }
      ]
    },
    {
      "type": "node",
      "name": "Legal Services",
      "value": 0,
      "children": [
        {
          "type": "leaf",
          "id": "sp_harneys",
          "name": "Harneys",
          "value": 50,
          "icon": "/icons/Service Providers/legal-services/harneys.jpg",
          "details": "Global offshore law firm providing legal and fiduciary services.",
          "link": "https://www.harneys.com/"
        },
        {
          "type": "leaf",
          "id": "sp_cole_frieman",
          "name": "Cole Freiman and Mallon",
          "value": 50,
          "icon": "/icons/Service Providers/legal-services/cole-frieman.jpg",
          "details": "Cole Freiman and Mallon LLP provides legal services to businesses in blockchain, crypto, and financial sectors, specializing in compliance and regulations.",
          "link": "https://colefrieman.com/"
        },
        {
          "type": "leaf",
          "id": "sp_carey_olsen",
          "name": "Carey Olsen",
          "value": 50,
          "icon": "/icons/Service Providers/legal-services/carey-olsen.webp",
          "details": "Offshore law firm specializing in corporate, funds, trusts, and private client services.",
          "link": "https://www.careyolsen.com/"
        }
      ]
    },
    {
      "type": "node",
      "name": "Blockchain Analytics",
      "value": 0,
      "children": [
        {
          "type": "leaf",
          "id": "sp_elliptic",
          "name": "Elliptic",
          "value": 50,
          "icon": "/icons/Service Providers/blockchain-analytics/elliptic.jpg",
          "details": "Blockchain analytics and cryptocurrency risk management.",
          "link": "https://www.elliptic.co/"
        },
        {
          "type": "leaf",
          "id": "sp_chainalysis",
          "name": "Chainalysis",
          "value": 50,
          "icon": "/icons/Service Providers/blockchain-analytics/chainalysis.png",
          "details": "Blockchain analytics company providing solutions for compliance and risk management.",
          "link": "https://www.chainalysis.com/"
        },
        {
          "type": "leaf",
          "id": "sp_scorechain",
          "name": "Scorechain",
          "value": 50,
          "icon": "/icons/Service Providers/blockchain-analytics/scorechain.jpg",
          "details": "Scorechain is a blockchain analytics firm providing compliance and risk management solutions to cryptocurrency businesses. They help assess fraudulent activities.",
          "link": "https://scorechain.com/"
        },
        {
          "type": "leaf",
          "id": "sp_trm_labs",
          "name": "TRM Labs",
          "value": 50,
          "icon": "/icons/Service Providers/blockchain-analytics/trm.jpg",
          "details": "TRM Labs offers blockchain analytics to detect and prevent crypto crime and enhance regulatory compliance for crypto businesses.",
          "link": "https://www.trmlabs.com/"
        },
        {
          "type": "leaf",
          "id": "sp_hexagate",
          "name": "Hexagate",
          "value": 50,
          "icon": "/icons/Service Providers/blockchain-analytics/hexagate.jpg",
          "details": "Hexagate provides blockchain analytics solutions for compliance, transaction monitoring, and market intelligence.",
          "link": "https://www.hexagate.com/"
        }
      ]
    },
    {
      "type": "node",
      "name": "Oracle Services",
      "value": 0,
      "children": [
        {
          "type": "leaf",
          "id": "sp_chainlink",
          "name": "Chainlink",
          "value": 50,
          "icon": "/icons/Service Providers/oracle-services/chainlink.png",
          "details": "Provider of decentralized oracle networks to securely connect smart contracts with external data.",
          "link": "https://chain.link/"
        },
        {
          "type": "leaf",
          "id": "sp_chronicle",
          "name": "Chronicle",
          "value": 50,
          "icon": "/icons/Service Providers/oracle-services/chronicle.png",
          "details": "Provider of on-chain verification solutions.",
          "link": "https://chroniclelabs.org/"
        }
      ]
    },
    {
      "type": "node",
      "name": "Financial Infrastructure",
      "value": 0,
      "children": [
        {
          "type": "leaf",
          "id": "sp_lseg",
          "name": "LSEG",
          "value": 50,
          "icon": "/icons/Service Providers/financial-infrastructure/lseg.png",
          "details": "Global financial markets infrastructure and data provider.",
          "link": "https://www.lseg.com/"
        }
      ]
    },
    {
      "type": "node",
      "name": "Credit Rating",
      "value": 0,
      "children": [
        {
          "type": "leaf",
          "id": "sp_moody",
          "name": "Moody's",
          "value": 50,
          "icon": "/icons/Service Providers/credit-rating/moodys.jpg",
          "details": "Global integrated risk assessment firm providing credit ratings, research, and risk analysis.",
          "link": "https://www.moodys.com/"
        }
      ]
    },
    {
      "type": "node",
      "name": "Exchange/Market Maker",
      "value": 0,
      "children": [
        {
          "type": "leaf",
          "id": "sp_b2c2",
          "name": "B2C2",
          "value": 50,
          "icon": "/icons/Service Providers/exchange-market/b2c2.jpg",
          "details": "B2C2 is a peer-to-peer (P2P) cryptocurrency exchange facilitating direct trading between individuals without an intermediary.",
          "link": "https://b2c2.com/"
        },
        {
          "type": "leaf",
          "id": "sp_keyrock",
          "name": "Keyrock",
          "value": 50,
          "icon": "/icons/Service Providers/exchange-market/keyrock.jpg",
          "details": "Keyrock is a digital asset market maker offering scalable and adaptable liquidity solutions to marketplaces and asset issuers across 85+ centralized and decentralized trading venues.",
          "link": "https://keyrock.eu/"
        },
        {
          "type": "leaf",
          "id": "sp_flow_traders",
          "name": "FlowTraders",
          "value": 50,
          "icon": "/icons/Service Providers/exchange-market/flowtraders.png",
          "details": "FlowTraders is a high-frequency trading (HFT) firm specializing in cryptocurrency markets. They provide liquidity and market making services to institutional investors.",
          "link": "https://www.flowtraders.com/"
        },
        {
          "type": "leaf",
          "id": "sp_hidden_road",
          "name": "Hidden Road",
          "value": 50,
          "icon": "/icons/Service Providers/exchange-market/hidden-road.webp",
          "details": "Hidden Road provides institutional liquidity for crypto markets, acting as a market maker for large-scale trades.",
          "link": "https://hiddenroad.com/"
        },
        {
          "type": "leaf",
          "id": "sp_falconx",
          "name": "FalconX",
          "value": 50,
          "icon": "/icons/Service Providers/exchange-market/falconx.jpg",
          "details": "FalconX provides liquidity and market-making services across digital assets, offering trading solutions for institutions.",
          "link": "https://www.falconx.io/"
        }
      ]
    },
    {
      "type": "node",
      "name": "KYC/AML Compliance",
      "value": 0,
      "children": [
        {
          "type": "leaf",
          "id": "sp_sumsub",
          "name": "Sumsub",
          "value": 50,
          "icon": "/icons/Service Providers/kyc-aml/sumsub.jpg",
          "details": "SumSub is a Know Your Customer (KYC) and Anti-Money Laundering (AML) compliance platform specializing in identity verification for cryptocurrency businesses.",
          "link": "https://sumsub.com/"
        },
        {
          "type": "leaf",
          "id": "sp_lmo_consulting",
          "name": "LMO Consulting",
          "value": 50,
          "icon": "/icons/Service Providers/kyc-aml/lmo.jpg",
          "details": "LMO Consulting specializes in KYC/AML compliance services to help businesses meet regulatory requirements in the financial and crypto sectors.",
          "link": "https://lmoservices.com.sg/"
        },
        {
          "type": "leaf",
          "id": "sp_nav_consulting",
          "name": "NAV Consulting",
          "value": 50,
          "icon": "/icons/Service Providers/kyc-aml/nav.jpg",
          "details": "NAV calculation services for accurately determining asset values.",
          "link": "https://www.navfundservices.com/"
        }
      ]
    }
  ]
}
